gemseo_template_editor_gui/__init__.py
gemseo_template_editor_gui-1.0.0.dist-info/CREDITS.rst
gemseo_template_editor_gui-1.0.0.dist-info/LICENSE.txt
gemseo_template_editor_gui-1.0.0.dist-info/METADATA
gemseo_template_editor_gui-1.0.0.dist-info/WHEEL
gemseo_template_editor_gui-1.0.0.dist-info/entry_points.txt
gemseo_template_editor_gui-1.0.0.dist-info/top_level.txt
gemseo_template_editor_gui-1.0.0.dist-info/RECORD
