Metadata-Version: 2.1
Name: gemseo-template-editor-gui
Version: 1.0.0
Summary: Capability for MDO under uncertainty.
Home-page: https://gitlab.com/gemseo
Author: GEMSEO team
Author-email: contact@gemseo.org
License: GNU Lesser General Public License v3
Project-URL: Source, https://gitlab.com/gemseo/dev/gemseo-template-grammar-editor
Project-URL: Tracker, https://gitlab.com/gemseo/dev/gemseo-template-grammar-editor/-/issues
Classifier: License :: OSI Approved :: GNU Lesser General Public License v3 (LGPLv3)
Classifier: Intended Audience :: Science/Research
Classifier: Topic :: Scientific/Engineering
Classifier: Operating System :: POSIX :: Linux
Classifier: Operating System :: MacOS
Classifier: Operating System :: Microsoft :: Windows
Classifier: Programming Language :: Python :: 3 :: Only
Classifier: Programming Language :: Python :: 3.8
Classifier: Programming Language :: Python :: 3.9
Classifier: Programming Language :: Python :: 3.10
Requires-Python: <3.11,>=3.8
License-File: LICENSE.txt
License-File: CREDITS.rst
Requires-Dist: pyside6 (<=6.4.2,>=6.3.0)
Provides-Extra: test
Requires-Dist: covdefaults ; extra == 'test'
Requires-Dist: pytest ; extra == 'test'
Requires-Dist: pytest-cov ; extra == 'test'
Requires-Dist: pytest-xdist ; extra == 'test'
